[{"title": "昆明汽车广播", "url": "http://ls.qingting.fm/live/1936/64k.m3u8", "poster": "http://pic.qingting.fm/2019/0810/20190810104648.jpeg", "content_id": 1936}, {"title": "云南交通之声", "url": "http://ls.qingting.fm/live/1928/64k.m3u8", "poster": "http://pic.qingting.fm/2015/0302/20150302154215601.png", "content_id": 1928}, {"title": "云南新闻广播", "url": "http://ls.qingting.fm/live/1926/64k.m3u8", "poster": "http://pic.qingting.fm/2019/0201/20190201071642.png", "content_id": 1926}, {"title": "FM1008新闻资讯广播", "url": "http://ls.qingting.fm/live/1934/64k.m3u8", "poster": "http://pic.qingting.fm/2015/0129/20150129171029457.JPG", "content_id": 1934}, {"title": "FM105城市资讯", "url": "http://ls.qingting.fm/live/1937/64k.m3u8", "poster": "http://pic.qingting.fm/2016/1227/20161227094524.jpeg", "content_id": 1937}, {"title": "云南私家车电台", "url": "http://ls.qingting.fm/live/1927/64k.m3u8", "poster": "http://pic.qingting.fm/2018/0408/20180408081824.jpeg", "content_id": 1927}, {"title": "FM99香格里拉之声", "url": "http://ls.qingting.fm/live/20139/64k.m3u8", "poster": "http://pic.qingting.fm/2013/0205/20130205050005969.jpg", "content_id": 20139}, {"title": "云南音乐广播", "url": "http://ls.qingting.fm/live/1929/64k.m3u8", "poster": "http://pic.qingting.fm/2016/0411/20160411120616688.png", "content_id": 1929}, {"title": "德宏民语综合广播", "url": "http://ls.qingting.fm/live/5021850/64k.m3u8", "poster": "http://pic.qingting.fm/2015/0324/2015032412092042.jpg", "content_id": 5021850}, {"title": "昆明NEW FM102.8", "url": "http://ls.qingting.fm/live/1935/64k.m3u8", "poster": "http://pic.qingting.fm/2013/channel_logo/1935.jpg", "content_id": 1935}, {"title": "红河交通广播 ", "url": "http://ls.qingting.fm/live/4994/64k.m3u8", "poster": "http://pic.qingting.fm/2016/0831/20160831105925.png", "content_id": 4994}, {"title": "昭通新闻综合广播", "url": "http://ls.qingting.fm/live/21249/64k.m3u8", "poster": "http://pic.qingting.fm/2016/0222/20160222160532121.png", "content_id": 21249}, {"title": "玉溪新闻综合广播FM102.4", "url": "http://ls.qingting.fm/live/5022031/64k.m3u8", "poster": "http://pic.qingting.fm/2017/1017/20171017081632.png", "content_id": 5022031}, {"title": "楚雄音乐广播", "url": "http://ls.qingting.fm/live/4035/64k.m3u8", "poster": "http://pic.qingting.fm/2018/1114/20181114085659.png", "content_id": 4035}, {"title": "红河综合广播", "url": "http://ls.qingting.fm/live/4033/64k.m3u8", "poster": "http://pic.qingting.fm/2011/1205/20111205010903385.jpg", "content_id": 4033}, {"title": "新知100知道分子频道", "url": "http://ls.qingting.fm/live/1930/64k.m3u8", "poster": "http://pic.qingting.fm/2017/0328/20170328095251.jpeg", "content_id": 1930}, {"title": "昭通交通旅游广播", "url": "http://ls.qingting.fm/live/21247/64k.m3u8", "poster": "http://pic.qingting.fm/2016/0103/20160103140207540.jpg", "content_id": 21247}, {"title": "文山交通广播", "url": "http://ls.qingting.fm/live/5021637/64k.m3u8", "poster": "http://pic.qingting.fm/2017/0302/20170302100932.jpeg", "content_id": 5021637}, {"title": "曲靖交通广播FM91.0", "url": "http://ls.qingting.fm/live/5022188/64k.m3u8", "poster": "http://pic.qingting.fm/2015/0420/2015042010225530.png", "content_id": 5022188}, {"title": "香格里拉之声", "url": "http://ls.qingting.fm/live/20137/64k.m3u8", "poster": "http://pic.qingting.fm/2015/0717/20150717145837114.jpg", "content_id": 20137}, {"title": "大理电台苍洱调频", "url": "http://ls.qingting.fm/live/1940/64k.m3u8", "poster": "http://pic.qingting.fm/2013/channel_logo/1940.jpg", "content_id": 1940}, {"title": "保山广播电视台FM98.7综合广播", "url": "http://ls.qingting.fm/live/5022446/64k.m3u8", "poster": "http://pic.qingting.fm/2015/0730/20150730170512634.jpg", "content_id": 5022446}, {"title": "云南民族广播", "url": "http://ls.qingting.fm/live/1933/64k.m3u8", "poster": "http://pic.qingting.fm/2011/0926/20110926113757107.jpg", "content_id": 1933}, {"title": "玉溪交通旅游广播FM87.7", "url": "http://ls.qingting.fm/live/20211563/64k.m3u8", "poster": "http://pic.qingting.fm/2017/1013/20171013181920284.png", "content_id": 20211563}, {"title": "楚雄综合广播", "url": "http://ls.qingting.fm/live/4030/64k.m3u8", "poster": "http://pic.qingting.fm/2018/1114/20181114085418.png", "content_id": 4030}, {"title": "曲靖综合广播", "url": "http://ls.qingting.fm/live/5022189/64k.m3u8", "poster": "http://pic.qingting.fm/2015/0420/20150420161229324.png", "content_id": 5022189}, {"title": "大理州电台新闻综合频率", "url": "http://ls.qingting.fm/live/20207747/64k.m3u8", "poster": "http://pic.qingting.fm/2017/0509/20170509155529879.jpg", "content_id": 20207747}, {"title": "镇雄新闻综合广播", "url": "http://ls.qingting.fm/live/20210752/64k.m3u8", "poster": "http://pic.qingting.fm/2017/0822/20170822110051790.jpg", "content_id": 20210752}, {"title": "德宏广播电视台综合广播", "url": "http://ls.qingting.fm/live/5021849/64k.m3u8", "poster": "http://pic.qingting.fm/2015/0313/20150313085840808.jpg", "content_id": 5021849}, {"title": "大理州电台旅游文化频率", "url": "http://ls.qingting.fm/live/20207748/64k.m3u8", "poster": "http://pic.qingting.fm/2017/0509/20170509155511764.jpg", "content_id": 20207748}, {"title": "云南少儿广播", "url": "http://ls.qingting.fm/live/1931/64k.m3u8", "poster": "http://pic.qingting.fm/2013/channel_logo/1931.jpg", "content_id": 1931}, {"title": "普洱广播电视台交通广播", "url": "http://ls.qingting.fm/live/20212429/64k.m3u8", "poster": "http://pic.qingting.fm/2019/0919/20190919034737.png", "content_id": 20212429}, {"title": "迪庆FM1047", "url": "http://ls.qingting.fm/live/15318506/64k.m3u8", "poster": "http://pic.qingting.fm/2016/0708/20160708180825888.png", "content_id": 15318506}, {"title": "弥勒广播电视台新闻综合广播", "url": "http://ls.qingting.fm/live/5022531/64k.m3u8", "poster": "http://pic.qingting.fm/2019/1014/20191014101111.png", "content_id": 5022531}, {"title": "普洱广播电视台综合广播", "url": "http://ls.qingting.fm/live/1938/64k.m3u8", "poster": "http://pic.qingting.fm/2013/channel_logo/1938.jpg", "content_id": 1938}, {"title": "开远人民广播电台", "url": "http://ls.qingting.fm/live/5022383/64k.m3u8", "poster": "http://pic.qingting.fm/2017/0801/20170801152747949.jpg", "content_id": 5022383}, {"title": "德宏交通旅游广播", "url": "http://ls.qingting.fm/live/5022548/64k.m3u8", "poster": "http://pic.qingting.fm/2017/0630/20170630091937.jpeg", "content_id": 5022548}, {"title": "巧家人民广播电台——白鹤之声", "url": "http://ls.qingting.fm/live/20211704/64k.m3u8", "poster": "http://pic.qingting.fm/2018/1010/20181010115515155.png", "content_id": 20211704}, {"title": "云南蒙自广播电台", "url": "http://ls.qingting.fm/live/5021599/64k.m3u8", "poster": "http://pic.qingting.fm/2017/0728/20170728114056.jpeg", "content_id": 5021599}, {"title": "芒市广播电台FM105.1", "url": "http://ls.qingting.fm/live/15318587/64k.m3u8", "poster": "http://pic.qingting.fm/2016/1008/20161008031351.jpeg", "content_id": 15318587}, {"title": "怒江广播电视台广播综合频率", "url": "http://ls.qingting.fm/live/15318176/64k.m3u8", "poster": "http://pic.qingting.fm/2015/1225/20151225175724432.png", "content_id": 15318176}, {"title": "大关人民广播电台新闻综合广播", "url": "http://ls.qingting.fm/live/20212212/64k.m3u8", "poster": "http://pic.qingting.fm/2019/0228/20190228172720480.jpg", "content_id": 20212212}]